pyHTTPRequestRouter/Attributes.py
pyHTTPRequestRouter/__init__.py
pyHTTPRequestRouter-0.1.4.dist-info/LICENSE.md
pyHTTPRequestRouter-0.1.4.dist-info/METADATA
pyHTTPRequestRouter-0.1.4.dist-info/WHEEL
pyHTTPRequestRouter-0.1.4.dist-info/top_level.txt
pyHTTPRequestRouter-0.1.4.dist-info/RECORD
