Metadata-Version: 2.1
Name: pyHTTPRequestRouter
Version: 0.1.4
Summary: A ReST API implementation (request router) using the pyHTTPInterface.
Home-page: https://github.com/Paebbels/pyHTTPRequestRouter
Author: Patrick Lehmann
Author-email: Paebbels@gmail.com
License: UNKNOWN
Project-URL: Documentation, https://pyHTTPRequestRouter.readthedocs.io/en/latest/
Project-URL: Source Code, https://github.com/Paebbels/pyHTTPRequestRouter
Project-URL: Issue Tracker, https://github.com/Paebbels/pyHTTPRequestRouter/issues
Keywords: Python3 HTTP Request-Router JSON ReST
Platform: UNKNOWN
Classifier: License :: OSI Approved :: Apache Software License
Classifier: Operating System :: OS Independent
Classifier: Programming Language :: Python :: 3 :: Only
Classifier: Programming Language :: Python :: 3.5
Classifier: Programming Language :: Python :: 3.6
Classifier: Programming Language :: Python :: 3.7
Classifier: Programming Language :: Python :: 3.8
Classifier: Development Status :: 2 - Pre-Alpha
Classifier: Intended Audience :: Developers
Classifier: Topic :: Internet :: WWW/HTTP :: HTTP Servers
Classifier: Topic :: Utilities
Requires-Python: >=3.5
Requires-Dist: py-flags
Requires-Dist: pyExceptions
Requires-Dist: pyAttributes
Requires-Dist: pyGenericPath
Requires-Dist: pyHTTPInterface
